larch/__init__.py
larch/_optional.py
larch/_version.py
larch/compiled.py
larch/datastats.py
larch/exceptions.py
larch/folding.py
larch/omx.py
larch/optimize.py
larch/roles.py
larch/shorts.py
larch/warning.py
larch/data_warehouse/MTCwork.csv.gz
larch/data_warehouse/artificial_long.csv.gz
larch/data_warehouse/exampville_demographics.csv.gz
larch/data_warehouse/exampville_employment.csv.gz
larch/data_warehouse/exampville_households.csv.gz
larch/data_warehouse/exampville_persons.csv.gz
larch/data_warehouse/exampville_skims.omx
larch/data_warehouse/exampville_taz.zip
larch/data_warehouse/exampville_tours.csv.gz
larch/data_warehouse/itinerary_data.csv.gz
larch/data_warehouse/swissmetro.csv.gz
larch/data_warehouse/vehicle_choice.parquet
larch/dataset/__init__.py
larch/dataset/choice_avail_reporting.py
larch/dataset/construct.py
larch/dataset/dim_names.py
larch/dataset/flow.py
larch/dataset/patch.py
larch/examples/__init__.py
larch/examples/generated/_001_mnl.py
larch/examples/generated/_002_motorized.py
larch/examples/generated/_003_zeroed_shared.py
larch/examples/generated/_005_motorized_travel_time.py
larch/examples/generated/_006_motorized_times.py
larch/examples/generated/_007_ovtt_by_distance.py
larch/examples/generated/_008_ttr.py
larch/examples/generated/_009_ttr_4.py
larch/examples/generated/_010_auto_per_hh.py
larch/examples/generated/_011_veh_per_worker.py
larch/examples/generated/_012_autos_per_adult.py
larch/examples/generated/_013_cbd.py
larch/examples/generated/_014_work_zone_density.py
larch/examples/generated/_015_cbd_and_work_density.py
larch/examples/generated/_016_cost_by_income.py
larch/examples/generated/_017A_market_seg.py
larch/examples/generated/_017B_alt_segmentation.py
larch/examples/generated/_017C_segmentation_males.py
larch/examples/generated/_017D_segmentation_female.py
larch/examples/generated/_017_mnl.py
larch/examples/generated/_022_nl.py
larch/examples/generated/_030_mnl_constrain.py
larch/examples/generated/_101_swissmetro_mnl.py
larch-6.0.42.dist-info/licenses/LICENSE
larch-6.0.42.dist-info/METADATA
larch-6.0.42.dist-info/WHEEL
larch-6.0.42.dist-info/top_level.txt
larch-6.0.42.dist-info/RECORD
